{"achievement.theEnd2":6,"stat.killEntity.Ghast":36,"achievement.acquireIron":262,"achievement.openInventory":2930,"stat.killEntity.Sheep":1,"stat.damageDealt":882066,"achievement.exploreAllBiomes":{"value":0,"progress":["Desert","Deep Ocean","Taiga","Extreme Hills","Ice Mountains","Savanna Plateau","DesertHills","Birch Forest","Savanna M","Savanna","Swampland","River","Sunflower Plains","Extreme Hills+","Flower Forest","Ocean","Plains","TaigaHills","Ice Plains","FrozenRiver","The End","Hell","ForestHills","Cold Taiga","Forest","Beach","Roofed Forest","Stone Beach","Cold Taiga Hills"]},"stat.killEntity.Bat":18,"achievement.cookFish":34,"stat.killEntity.Cow":46,"achievement.portal":432,"stat.fallOneCm":731797,"stat.flyOneCm":1204521,"achievement.buildWorkBench":19,"stat.junkFished":1,"achievement.buildPickaxe":167,"stat.treasureFished":11,"achievement.overkill":323,"achievement.buildFurnace":99,"stat.damageTaken":32375,"achievement.killCow":28,"stat.climbOneCm":85644,"achievement.potion":148,"stat.killEntity.Chicken":58,"achievement.theEnd":2,"stat.drop":240,"achievement.enchantments":1,"stat.entityKilledBy.PigZombie":2,"stat.killEntity.Enderman":57,"stat.leaveGame":151,"stat.diveOneCm":5211623,"achievement.mineWood":233,"achievement.buildBetterPickaxe":166,"stat.killEntity.Spider":98,"achievement.killEnemy":3858,"stat.killEntity.Slime":190,"achievement.diamonds":201,"achievement.ghast":5,"stat.killEntity.LavaSlime":332,"stat.killEntity.Creeper":148,"stat.killEntity.PigZombie":1390,"stat.playOneMinute":8406946,"stat.boatOneCm":3277372,"achievement.buildSword":11,"stat.killEntity.Pig":3,"stat.deaths":10,"stat.fishCaught":247,"stat.swimOneCm":2544018,"stat.mobKills":4106,"stat.killEntity.Skeleton":520,"stat.horseOneCm":777789,"stat.walkOneCm":51482243,"stat.killEntity.Zombie":338,"stat.minecartOneCm":46973,"stat.killEntity.Silverfish":9,"achievement.blazeRod":391,"stat.jump":41966,"stat.killEntity.Blaze":493,"stat.killEntity.Witch":12,"stat.entityKilledBy.Zombie":4,"stat.killEntity.Squid":4,"stat.killEntity.CaveSpider":6}